{
  "allFiles": [
    {
      "file": "/storage/emulated/0/AndroidIDEProjects/extratools_1.21.1/build.gradle",
      "selection": {
        "end": {
          "column": 11,
          "index": 1247,
          "line": 38
        },
        "start": {
          "column": 11,
          "index": 1247,
          "line": 38
        }
      }
    },
    {
      "file": "/storage/emulated/0/AndroidIDEProjects/extratools_1.21.1/.git/config",
      "selection": {
        "end": {
          "column": 112,
          "index": 288,
          "line": 9
        },
        "start": {
          "column": 112,
          "index": 288,
          "line": 9
        }
      }
    }
  ],
  "selectedFile": "/storage/emulated/0/AndroidIDEProjects/extratools_1.21.1/.git/config"
}